{"cameraMode":{"drawMode":0,"name":"Shaded","section":"Shading Mode"},"sceneLighting":true,"audioPlay":false,"sceneViewState":{"m_AlwaysRefresh":false,"showFog":true,"showSkybox":true,"showFlares":true,"showImageEffects":true,"showParticleSystems":true,"showVisualEffectGraphs":true,"m_FxEnabled":true},"in2DMode":false,"pivot":{"x":1.2964229583740235,"y":6.301671981811523,"z":-4.775407791137695},"rotation":{"x":-0.03381927311420441,"y":0.8907517194747925,"z":-0.067209392786026,"w":-0.44822007417678835},"size":5.453064441680908,"orthographic":false}